[
  {
    "author": "marce2santos",
    "link_thumb": "https://live.staticflickr.com/65535/51669779701_aabaaea8b6_o.gif",
    "link_bin": "https://github.com/lmbstudiocontact/mb6_0/raw/main/786.bin",
    "id_bin": "786",
    "list_language": [],
    "array_tags": [],
    "list_album": [
      {
        "id_album": "2433880",
        "link_thumb": "https://live.staticflickr.com/65535/51669779701_aabaaea8b6_o.gif",
        "title": "None"
      }
    ]
  },
  {
    "author": "MAXSTILL",
    "link_thumb": "https://live.staticflickr.com/65535/51670563030_b7cf1a3fe0_o.gif",
    "link_bin": "https://github.com/lmbstudiocontact/mb6_0/raw/main/331.bin",
    "id_bin": "331",
    "list_language": [],
    "array_tags": [
      "date",
      "games",
      "battery"
    ],
    "list_album": [
      {
        "id_album": "2211858",
        "link_thumb": "https://live.staticflickr.com/65535/51670563030_b7cf1a3fe0_o.gif",
        "title": "Game"
      }
    ]
  },
  {
    "author": "ZanarkTempest",
    "link_thumb": "https://live.staticflickr.com/65535/51669853093_f8503f1238_o.gif",
    "link_bin": "https://github.com/lmbstudiocontact/mb6_1/raw/main/2127.bin",
    "id_bin": "2127",
    "list_language": [],
    "array_tags": [
      "heartrate",
      "anime"
    ],
    "list_album": [
      {
        "id_album": "63410260",
        "link_thumb": "https://live.staticflickr.com/65535/51669853093_f8503f1238_o.gif",
        "title": "Anime"
      }
    ]
  },
  {
    "author": "LMB Studio",
    "link_thumb": "https://live.staticflickr.com/65535/51677264916_d1ef6ab417_o.gif",
    "link_bin": "https://github.com/lmbstudiocontact/mb6_7/raw/main/OnePieceAnime13_M6_2.bin",
    "id_bin": "OnePieceAnime13_M6_2",
    "list_language": [
      {
        "author": "LMB Studio",
        "link_thumb": "https://live.staticflickr.com/65535/51678146460_6924221ab3_o.gif",
        "link_bin": "https://github.com/lmbstudiocontact/mb6_7/raw/main/OnePieceAnime13_M6_2_English.bin",
        "name_language": "English",
        "id_bin_language": "OnePieceAnime13_M6_2_English"
      },
      {
        "author": "LMB Studio",
        "link_thumb": "https://live.staticflickr.com/65535/51677265341_7228ff664c_o.gif",
        "link_bin": "https://github.com/lmbstudiocontact/mb6_3/raw/main/OnePieceAnime13_M6_2_Portuguese.bin",
        "name_language": "Portuguese",
        "id_bin_language": "OnePieceAnime13_M6_2_Portuguese"
      },
      {
        "author": "LMB Studio",
        "link_thumb": "https://live.staticflickr.com/65535/51676459677_2313743bbc_o.gif",
        "link_bin": "https://github.com/lmbstudiocontact/mb6_3/raw/main/OnePieceAnime13_M6_2_Russian.bin",
        "name_language": "Russian",
        "id_bin_language": "OnePieceAnime13_M6_2_Russian"
      },
      {
        "author": "LMB Studio",
        "link_thumb": "https://live.staticflickr.com/65535/51677514253_0ae5907dcb_o.gif",
        "link_bin": "https://github.com/lmbstudiocontact/mb6_3/raw/main/OnePieceAnime13_M6_2_Spanish.bin",
        "name_language": "Spanish",
        "id_bin_language": "OnePieceAnime13_M6_2_Spanish"
      }
    ],
    "array_tags": [],
    "list_album": [
      {
        "id_album": "1669710643",
        "link_thumb": "https://live.staticflickr.com/65535/51677264916_d1ef6ab417_o.gif",
        "title": "One Piece Anime_M6_2"
      }
    ]
  },
  {
    "author": "joaokit",
    "link_thumb": "https://live.staticflickr.com/65535/51670559840_d3273696c7_o.gif",
    "link_bin": "https://github.com/lmbstudiocontact/mb6_0/raw/main/320.bin",
    "id_bin": "320",
    "list_language": [],
    "array_tags": [
      "date",
      "apple",
      "heartrate",
      "english",
      "watchos"
    ],
    "list_album": [
      {
        "id_album": "-2075887794",
        "link_thumb": "https://live.staticflickr.com/65535/51670559840_d3273696c7_o.gif",
        "title": "Cartoon"
      }
    ]
  },
  {
    "author": "LMB Studio",
    "link_thumb": "https://live.staticflickr.com/65535/51677653033_5f81632d3c_o.gif",
    "link_bin": "https://github.com/lmbstudiocontact/mb6_3/raw/main/PlantsVsZombies0_M6_2.bin",
    "id_bin": "PlantsVsZombies0_M6_2",
    "list_language": [
      {
        "author": "LMB Studio",
        "link_thumb": "https://live.staticflickr.com/65535/51677653233_5822d9d281_o.gif",
        "link_bin": "https://github.com/lmbstudiocontact/mb6_3/raw/main/PlantsVsZombies0_M6_2_English.bin",
        "name_language": "English",
        "id_bin_language": "PlantsVsZombies0_M6_2_English"
      },
      {
        "author": "LMB Studio",
        "link_thumb": "https://live.staticflickr.com/65535/51678077524_ac929b11fd_o.gif",
        "link_bin": "https://github.com/lmbstudiocontact/mb6_3/raw/main/PlantsVsZombies0_M6_2_Portuguese.bin",
        "name_language": "Portuguese",
        "id_bin_language": "PlantsVsZombies0_M6_2_Portuguese"
      },
      {
        "author": "LMB Studio",
        "link_thumb": "https://live.staticflickr.com/65535/51678077829_c43c001602_o.gif",
        "link_bin": "https://github.com/lmbstudiocontact/mb6_3/raw/main/PlantsVsZombies0_M6_2_Russian.bin",
        "name_language": "Russian",
        "id_bin_language": "PlantsVsZombies0_M6_2_Russian"
      },
      {
        "author": "LMB Studio",
        "link_thumb": "https://live.staticflickr.com/65535/51677653993_8bde897b7e_o.gif",
        "link_bin": "https://github.com/lmbstudiocontact/mb6_3/raw/main/PlantsVsZombies0_M6_2_Spanish.bin",
        "name_language": "Spanish",
        "id_bin_language": "PlantsVsZombies0_M6_2_Spanish"
      }
    ],
    "array_tags": [],
    "list_album": [
      {
        "id_album": "-1038543655",
        "link_thumb": "https://live.staticflickr.com/65535/51677653033_5f81632d3c_o.gif",
        "title": "Plants Vs Zombies_M6_2"
      }
    ]
  },
  {
    "author": "Zdan",
    "link_thumb": "https://live.staticflickr.com/65535/51668695187_1251b4030a_o.gif",
    "link_bin": "https://github.com/lmbstudiocontact/mb6_0/raw/main/1313.bin",
    "id_bin": "1313",
    "list_language": [],
    "array_tags": [
      "date",
      "distance",
      "alarm",
      "weather",
      "health",
      "time",
      "battery",
      "day",
      "steps"
    ],
    "list_album": [
      {
        "id_album": "2433880",
        "link_thumb": "https://live.staticflickr.com/65535/51668695187_1251b4030a_o.gif",
        "title": "None"
      }
    ]
  },
  {
    "author": "krewlworld",
    "link_thumb": "https://live.staticflickr.com/65535/51668790982_ac93da81ea_o.gif",
    "link_bin": "https://github.com/lmbstudiocontact/mb6_1/raw/main/1987.bin",
    "id_bin": "1987",
    "list_language": [],
    "array_tags": [
      "digital",
      "date",
      "heartrate",
      "clear",
      "simple",
      "battery",
      "clean",
      "steps",
      "minimal",
      "bluetooth",
      "legible",
      "weather",
      "lock",
      "dnd",
      "day"
    ],
    "list_album": [
      {
        "id_album": "2433880",
        "link_thumb": "https://live.staticflickr.com/65535/51668790982_ac93da81ea_o.gif",
        "title": "None"
      }
    ]
  },
  {
    "author": "LMB Studio",
    "link_thumb": "https://live.staticflickr.com/65535/51675690972_136541377f_o.gif",
    "link_bin": "https://github.com/lmbstudiocontact/mb6_5/raw/main/CuteArt67_M6_2.bin",
    "id_bin": "CuteArt67_M6_2",
    "list_language": [
      {
        "author": "LMB Studio",
        "link_thumb": "https://live.staticflickr.com/65535/51676739263_c3fd99ea36_o.gif",
        "link_bin": "https://github.com/lmbstudiocontact/mb6_5/raw/main/CuteArt67_M6_2_English.bin",
        "name_language": "English",
        "id_bin_language": "CuteArt67_M6_2_English"
      },
      {
        "author": "LMB Studio",
        "link_thumb": "https://live.staticflickr.com/65535/51676495041_49ded3b52c_o.gif",
        "link_bin": "https://github.com/lmbstudiocontact/mb6_5/raw/main/CuteArt67_M6_2_Portuguese.bin",
        "name_language": "Portuguese",
        "id_bin_language": "CuteArt67_M6_2_Portuguese"
      },
      {
        "author": "LMB Studio",
        "link_thumb": "https://live.staticflickr.com/65535/51676495256_a1cd51fdf1_o.gif",
        "link_bin": "https://github.com/lmbstudiocontact/mb6_5/raw/main/CuteArt67_M6_2_Russian.bin",
        "name_language": "Russian",
        "id_bin_language": "CuteArt67_M6_2_Russian"
      },
      {
        "author": "LMB Studio",
        "link_thumb": "https://live.staticflickr.com/65535/51676495521_035d824f78_o.gif",
        "link_bin": "https://github.com/lmbstudiocontact/mb6_5/raw/main/CuteArt67_M6_2_Spanish.bin",
        "name_language": "Spanish",
        "id_bin_language": "CuteArt67_M6_2_Spanish"
      }
    ],
    "array_tags": [],
    "list_album": [
      {
        "id_album": "195512437",
        "link_thumb": "https://live.staticflickr.com/65535/51675690972_136541377f_o.gif",
        "title": "Cute Art_M6_2"
      }
    ]
  },
  {
    "author": "LMB Studio",
    "link_thumb": "https://live.staticflickr.com/65535/51676778007_a22a836ea0_o.gif",
    "link_bin": "https://github.com/lmbstudiocontact/mb6_4/raw/main/Rio214_M6_2.bin",
    "id_bin": "Rio214_M6_2",
    "list_language": [
      {
        "author": "LMB Studio",
        "link_thumb": "https://live.staticflickr.com/65535/51676778232_29f5006fc1_o.gif",
        "link_bin": "https://github.com/lmbstudiocontact/mb6_4/raw/main/Rio214_M6_2_English.bin",
        "name_language": "English",
        "id_bin_language": "Rio214_M6_2_English"
      },
      {
        "author": "LMB Studio",
        "link_thumb": "https://live.staticflickr.com/65535/51677833453_bf5e935a1e_o.gif",
        "link_bin": "https://github.com/lmbstudiocontact/mb6_4/raw/main/Rio214_M6_2_Portuguese.bin",
        "name_language": "Portuguese",
        "id_bin_language": "Rio214_M6_2_Portuguese"
      },
      {
        "author": "LMB Studio",
        "link_thumb": "https://live.staticflickr.com/65535/51676778627_b3c9eddfd0_o.gif",
        "link_bin": "https://github.com/lmbstudiocontact/mb6_4/raw/main/Rio214_M6_2_Russian.bin",
        "name_language": "Russian",
        "id_bin_language": "Rio214_M6_2_Russian"
      },
      {
        "author": "LMB Studio",
        "link_thumb": "https://live.staticflickr.com/65535/51677833813_ed0e86131b_o.gif",
        "link_bin": "https://github.com/lmbstudiocontact/mb6_4/raw/main/Rio214_M6_2_Spanish.bin",
        "name_language": "Spanish",
        "id_bin_language": "Rio214_M6_2_Spanish"
      }
    ],
    "array_tags": [],
    "list_album": [
      {
        "id_album": "296910609",
        "link_thumb": "https://live.staticflickr.com/65535/51676778007_a22a836ea0_o.gif",
        "title": "Rio 2_M6_2"
      }
    ]
  },
  {
    "author": "Rosta949",
    "link_thumb": "https://live.staticflickr.com/65535/51669539481_69c2fb103b_o.gif",
    "link_bin": "https://github.com/lmbstudiocontact/mb6_1/raw/main/1691.bin",
    "id_bin": "1691",
    "list_language": [],
    "array_tags": [
      "date",
      "bluetooth",
      "weather",
      "weekday",
      "battery"
    ],
    "list_album": [
      {
        "id_album": "2433880",
        "link_thumb": "https://live.staticflickr.com/65535/51669539481_69c2fb103b_o.gif",
        "title": "None"
      }
    ]
  },
  {
    "author": "LMB Studio",
    "link_thumb": "https://live.staticflickr.com/65535/51677321645_3b07ede70d_o.gif",
    "link_bin": "https://github.com/lmbstudiocontact/mb6_8/raw/main/CuteArt26_M6_2.bin",
    "id_bin": "CuteArt26_M6_2",
    "list_language": [
      {
        "author": "LMB Studio",
        "link_thumb": "https://live.staticflickr.com/65535/51676443551_9f157a8237_o.gif",
        "link_bin": "https://github.com/lmbstudiocontact/mb6_8/raw/main/CuteArt26_M6_2_English.bin",
        "name_language": "English",
        "id_bin_language": "CuteArt26_M6_2_English"
      },
      {
        "author": "LMB Studio",
        "link_thumb": "https://live.staticflickr.com/65535/51676688198_9655d5025f_o.gif",
        "link_bin": "https://github.com/lmbstudiocontact/mb6_8/raw/main/CuteArt26_M6_2_Portuguese.bin",
        "name_language": "Portuguese",
        "id_bin_language": "CuteArt26_M6_2_Portuguese"
      },
      {
        "author": "LMB Studio",
        "link_thumb": "https://live.staticflickr.com/65535/51677322345_ab02f1f742_o.gif",
        "link_bin": "https://github.com/lmbstudiocontact/mb6_8/raw/main/CuteArt26_M6_2_Russian.bin",
        "name_language": "Russian",
        "id_bin_language": "CuteArt26_M6_2_Russian"
      },
      {
        "author": "LMB Studio",
        "link_thumb": "https://live.staticflickr.com/65535/51675640287_558e7341ba_o.gif",
        "link_bin": "https://github.com/lmbstudiocontact/mb6_8/raw/main/CuteArt26_M6_2_Spanish.bin",
        "name_language": "Spanish",
        "id_bin_language": "CuteArt26_M6_2_Spanish"
      }
    ],
    "array_tags": [],
    "list_album": [
      {
        "id_album": "195512437",
        "link_thumb": "https://live.staticflickr.com/65535/51677321645_3b07ede70d_o.gif",
        "title": "Cute Art_M6_2"
      }
    ]
  },
  {
    "author": "Spookus",
    "link_thumb": "https://live.staticflickr.com/65535/51670363865_a00429797f_o.gif",
    "link_bin": "https://github.com/lmbstudiocontact/mb6_0/raw/main/1219.bin",
    "id_bin": "1219",
    "list_language": [],
    "array_tags": [
      "dark"
    ],
    "list_album": [
      {
        "id_album": "2433880",
        "link_thumb": "https://live.staticflickr.com/65535/51670363865_a00429797f_o.gif",
        "title": "None"
      }
    ]
  },
  {
    "author": "Вепрь",
    "link_thumb": "https://live.staticflickr.com/65535/51669751468_cd5ebec16a_o.gif",
    "link_bin": "https://github.com/lmbstudiocontact/mb6_0/raw/main/1429.bin",
    "id_bin": "1429",
    "list_language": [],
    "array_tags": [
      "digital",
      "date",
      "distance",
      "heartrate",
      "weather",
      "calories",
      "battery",
      "steps"
    ],
    "list_album": [
      {
        "id_album": "2433880",
        "link_thumb": "https://live.staticflickr.com/65535/51669751468_cd5ebec16a_o.gif",
        "title": "None"
      }
    ]
  },
  {
    "author": "zuggi1985",
    "link_thumb": "https://live.staticflickr.com/65535/51669669506_bd69192327_o.gif",
    "link_bin": "https://github.com/lmbstudiocontact/mb6_0/raw/main/272.bin",
    "id_bin": "272",
    "list_language": [],
    "array_tags": [
      "zuggi"
    ],
    "list_album": [
      {
        "id_album": "2433880",
        "link_thumb": "https://live.staticflickr.com/65535/51669669506_bd69192327_o.gif",
        "title": "None"
      }
    ]
  },
  {
    "author": "LMB Studio",
    "link_thumb": "https://live.staticflickr.com/65535/51676213242_f46ea3cfed_o.gif",
    "link_bin": "https://github.com/lmbstudiocontact/mb6_6/raw/main/Kitty\u0026MyMelody43_M6_2.bin",
    "id_bin": "Kitty\u0026MyMelody43_M6_2",
    "list_language": [
      {
        "author": "LMB Studio",
        "link_thumb": "https://live.staticflickr.com/65535/51677689084_66928fd6c1_o.gif",
        "link_bin": "https://github.com/lmbstudiocontact/mb6_6/raw/main/Kitty\u0026MyMelody43_M6_2_English.bin",
        "name_language": "English",
        "id_bin_language": "Kitty\u0026MyMelody43_M6_2_English"
      },
      {
        "author": "LMB Studio",
        "link_thumb": "https://live.staticflickr.com/65535/51677264093_8aa20565e6_o.gif",
        "link_bin": "https://github.com/lmbstudiocontact/mb6_6/raw/main/Kitty\u0026MyMelody43_M6_2_Portuguese.bin",
        "name_language": "Portuguese",
        "id_bin_language": "Kitty\u0026MyMelody43_M6_2_Portuguese"
      },
      {
        "author": "LMB Studio",
        "link_thumb": "https://live.staticflickr.com/65535/51677264378_68b81d3286_o.gif",
        "link_bin": "https://github.com/lmbstudiocontact/mb6_6/raw/main/Kitty\u0026MyMelody43_M6_2_Russian.bin",
        "name_language": "Russian",
        "id_bin_language": "Kitty\u0026MyMelody43_M6_2_Russian"
      },
      {
        "author": "LMB Studio",
        "link_thumb": "https://live.staticflickr.com/65535/51677689989_d57bbc5018_o.gif",
        "link_bin": "https://github.com/lmbstudiocontact/mb6_6/raw/main/Kitty\u0026MyMelody43_M6_2_Spanish.bin",
        "name_language": "Spanish",
        "id_bin_language": "Kitty\u0026MyMelody43_M6_2_Spanish"
      }
    ],
    "array_tags": [],
    "list_album": [
      {
        "id_album": "1352454006",
        "link_thumb": "https://live.staticflickr.com/65535/51676213242_f46ea3cfed_o.gif",
        "title": "Kitty \u0026 My Melody_M6_2"
      }
    ]
  },
  {
    "author": "LMB Studio",
    "link_thumb": "https://live.staticflickr.com/65535/51678235279_91ccd709c3_o.gif",
    "link_bin": "https://github.com/lmbstudiocontact/mb6_4/raw/main/Ragnarok13_M6_2.bin",
    "id_bin": "Ragnarok13_M6_2",
    "list_language": [
      {
        "author": "LMB Studio",
        "link_thumb": "https://live.staticflickr.com/65535/51678235424_933b3c7b06_o.gif",
        "link_bin": "https://github.com/lmbstudiocontact/mb6_4/raw/main/Ragnarok13_M6_2_English.bin",
        "name_language": "English",
        "id_bin_language": "Ragnarok13_M6_2_English"
      },
      {
        "author": "LMB Studio",
        "link_thumb": "https://live.staticflickr.com/65535/51677811848_2e68a8d53c_o.gif",
        "link_bin": "https://github.com/lmbstudiocontact/mb6_4/raw/main/Ragnarok13_M6_2_Portuguese.bin",
        "name_language": "Portuguese",
        "id_bin_language": "Ragnarok13_M6_2_Portuguese"
      },
      {
        "author": "LMB Studio",
        "link_thumb": "https://live.staticflickr.com/65535/51677812033_bc4e53b823_o.gif",
        "link_bin": "https://github.com/lmbstudiocontact/mb6_4/raw/main/Ragnarok13_M6_2_Russian.bin",
        "name_language": "Russian",
        "id_bin_language": "Ragnarok13_M6_2_Russian"
      },
      {
        "author": "LMB Studio",
        "link_thumb": "https://live.staticflickr.com/65535/51678235909_a9a14e7668_o.gif",
        "link_bin": "https://github.com/lmbstudiocontact/mb6_4/raw/main/Ragnarok13_M6_2_Spanish.bin",
        "name_language": "Spanish",
        "id_bin_language": "Ragnarok13_M6_2_Spanish"
      }
    ],
    "array_tags": [],
    "list_album": [
      {
        "id_album": "1272388472",
        "link_thumb": "https://live.staticflickr.com/65535/51678235279_91ccd709c3_o.gif",
        "title": "Ragnarok_M6_2"
      }
    ]
  },
  {
    "author": "ZanarkTempest",
    "link_thumb": "https://live.staticflickr.com/65535/51668758652_d37e817c1a_o.gif",
    "link_bin": "https://github.com/lmbstudiocontact/mb6_1/raw/main/1787.bin",
    "id_bin": "1787",
    "list_language": [],
    "array_tags": [
      "anime"
    ],
    "list_album": [
      {
        "id_album": "63410260",
        "link_thumb": "https://live.staticflickr.com/65535/51668758652_d37e817c1a_o.gif",
        "title": "Anime"
      }
    ]
  },
  {
    "author": "brunello",
    "link_thumb": "https://live.staticflickr.com/65535/51670409739_27dbb09e8c_o.gif",
    "link_bin": "https://github.com/lmbstudiocontact/mb6_0/raw/main/506.bin",
    "id_bin": "506",
    "list_language": [],
    "array_tags": [
      "digital",
      "date",
      "analog",
      "seconds",
      "heartrate",
      "battery",
      "steps"
    ],
    "list_album": [
      {
        "id_album": "2433880",
        "link_thumb": "https://live.staticflickr.com/65535/51670409739_27dbb09e8c_o.gif",
        "title": "None"
      }
    ]
  },
  {
    "author": "parasupaman",
    "link_thumb": "https://live.staticflickr.com/65535/51670392400_cf19d9f4de_o.gif",
    "link_bin": "https://github.com/lmbstudiocontact/mb6_0/raw/main/144.bin",
    "id_bin": "144",
    "list_language": [],
    "array_tags": [
      "digital",
      "date",
      "time",
      "battery",
      "day"
    ],
    "list_album": [
      {
        "id_album": "2433880",
        "link_thumb": "https://live.staticflickr.com/65535/51670392400_cf19d9f4de_o.gif",
        "title": "None"
      }
    ]
  },
  {
    "author": ".Kosmik",
    "link_thumb": "https://live.staticflickr.com/65535/51669777733_56c94bf246_o.gif",
    "link_bin": "https://github.com/lmbstudiocontact/mb6_0/raw/main/1664.bin",
    "id_bin": "1664",
    "list_language": [],
    "array_tags": [
      "digital",
      "date",
      "battery",
      "steps"
    ],
    "list_album": [
      {
        "id_album": "2433880",
        "link_thumb": "https://live.staticflickr.com/65535/51669777733_56c94bf246_o.gif",
        "title": "None"
      }
    ]
  },
  {
    "author": "LMB Studio",
    "link_thumb": "https://live.staticflickr.com/65535/51677045236_295af7dabb_o.gif",
    "link_bin": "https://github.com/lmbstudiocontact/mb6_7/raw/main/Kitty\u0026MyMelody65_M6_2.bin",
    "id_bin": "Kitty\u0026MyMelody65_M6_2",
    "list_language": [
      {
        "author": "LMB Studio",
        "link_thumb": "https://live.staticflickr.com/65535/51677926920_8e2402ee75_o.gif",
        "link_bin": "https://github.com/lmbstudiocontact/mb6_7/raw/main/Kitty\u0026MyMelody65_M6_2_English.bin",
        "name_language": "English",
        "id_bin_language": "Kitty\u0026MyMelody65_M6_2_English"
      },
      {
        "author": "LMB Studio",
        "link_thumb": "https://live.staticflickr.com/65535/51677045641_b91c463512_o.gif",
        "link_bin": "https://github.com/lmbstudiocontact/mb6_7/raw/main/Kitty\u0026MyMelody65_M6_2_Portuguese.bin",
        "name_language": "Portuguese",
        "id_bin_language": "Kitty\u0026MyMelody65_M6_2_Portuguese"
      },
      {
        "author": "LMB Studio",
        "link_thumb": "https://live.staticflickr.com/65535/51677717504_a2ffc9c145_o.gif",
        "link_bin": "https://github.com/lmbstudiocontact/mb6_7/raw/main/Kitty\u0026MyMelody65_M6_2_Russian.bin",
        "name_language": "Russian",
        "id_bin_language": "Kitty\u0026MyMelody65_M6_2_Russian"
      },
      {
        "author": "LMB Studio",
        "link_thumb": "https://live.staticflickr.com/65535/51677717674_4a67a8cdbf_o.gif",
        "link_bin": "https://github.com/lmbstudiocontact/mb6_7/raw/main/Kitty\u0026MyMelody65_M6_2_Spanish.bin",
        "name_language": "Spanish",
        "id_bin_language": "Kitty\u0026MyMelody65_M6_2_Spanish"
      }
    ],
    "array_tags": [],
    "list_album": [
      {
        "id_album": "1352454006",
        "link_thumb": "https://live.staticflickr.com/65535/51677045236_295af7dabb_o.gif",
        "title": "Kitty \u0026 My Melody_M6_2"
      }
    ]
  },
  {
    "author": "Rosta949",
    "link_thumb": "https://live.staticflickr.com/65535/51670130823_7dcb827eb0_o.gif",
    "link_bin": "https://github.com/lmbstudiocontact/mb6_1/raw/main/2347.bin",
    "id_bin": "2347",
    "list_language": [],
    "array_tags": [
      "digital",
      "date",
      "weekday",
      "time",
      "battery",
      "status",
      "animation"
    ],
    "list_album": [
      {
        "id_album": "2433880",
        "link_thumb": "https://live.staticflickr.com/65535/51670130823_7dcb827eb0_o.gif",
        "title": "None"
      }
    ]
  },
  {
    "author": "ZanarkTempest",
    "link_thumb": "https://live.staticflickr.com/65535/51668831772_5bcdfec963_o.gif",
    "link_bin": "https://github.com/lmbstudiocontact/mb6_1/raw/main/2255.bin",
    "id_bin": "2255",
    "list_language": [],
    "array_tags": [
      "cartoon",
      "heartrate",
      "serie",
      "games",
      "batman",
      "steps"
    ],
    "list_album": [
      {
        "id_album": "-2075887794",
        "link_thumb": "https://live.staticflickr.com/65535/51668831772_5bcdfec963_o.gif",
        "title": "Cartoon"
      }
    ]
  },
  {
    "author": "LMB Studio",
    "link_thumb": "https://live.staticflickr.com/65535/51675833582_be07ac5f2d_o.gif",
    "link_bin": "https://github.com/lmbstudiocontact/mb6_5/raw/main/DragonArt2_M6_2.bin",
    "id_bin": "DragonArt2_M6_2",
    "list_language": [
      {
        "author": "LMB Studio",
        "link_thumb": "https://live.staticflickr.com/65535/51676883243_a2f4437bf8_o.gif",
        "link_bin": "https://github.com/lmbstudiocontact/mb6_5/raw/main/DragonArt2_M6_2_English.bin",
        "name_language": "English",
        "id_bin_language": "DragonArt2_M6_2_English"
      },
      {
        "author": "LMB Studio",
        "link_thumb": "https://live.staticflickr.com/65535/51676883558_3c417fa048_o.gif",
        "link_bin": "https://github.com/lmbstudiocontact/mb6_5/raw/main/DragonArt2_M6_2_Portuguese.bin",
        "name_language": "Portuguese",
        "id_bin_language": "DragonArt2_M6_2_Portuguese"
      },
      {
        "author": "LMB Studio",
        "link_thumb": "https://live.staticflickr.com/65535/51676638216_1dfd84ff20_o.gif",
        "link_bin": "https://github.com/lmbstudiocontact/mb6_5/raw/main/DragonArt2_M6_2_Russian.bin",
        "name_language": "Russian",
        "id_bin_language": "DragonArt2_M6_2_Russian"
      },
      {
        "author": "LMB Studio",
        "link_thumb": "https://live.staticflickr.com/65535/51675834632_a7115b8ae2_o.gif",
        "link_bin": "https://github.com/lmbstudiocontact/mb6_5/raw/main/DragonArt2_M6_2_Spanish.bin",
        "name_language": "Spanish",
        "id_bin_language": "DragonArt2_M6_2_Spanish"
      }
    ],
    "array_tags": [],
    "list_album": [
      {
        "id_album": "-1267433787",
        "link_thumb": "https://live.staticflickr.com/65535/51675833582_be07ac5f2d_o.gif",
        "title": "Dragon Art_M6_2"
      }
    ]
  },
  {
    "author": "Rosta949",
    "link_thumb": "https://live.staticflickr.com/65535/51668859347_acaa75985b_o.gif",
    "link_bin": "https://github.com/lmbstudiocontact/mb6_1/raw/main/2401.bin",
    "id_bin": "2401",
    "list_language": [],
    "array_tags": [
      "date",
      "digital",
      "analog",
      "weekday",
      "battery",
      "status",
      "animation"
    ],
    "list_album": [
      {
        "id_album": "2433880",
        "link_thumb": "https://live.staticflickr.com/65535/51668859347_acaa75985b_o.gif",
        "title": "None"
      }
    ]
  },
  {
    "author": "LMB Studio",
    "link_thumb": "https://live.staticflickr.com/65535/51677079843_1303a93716_o.gif",
    "link_bin": "https://github.com/lmbstudiocontact/mb6_6/raw/main/HalloweenGhostWitch18_M6_2.bin",
    "id_bin": "HalloweenGhostWitch18_M6_2",
    "list_language": [
      {
        "author": "LMB Studio",
        "link_thumb": "https://live.staticflickr.com/65535/51677505224_fff67e1ef7_o.gif",
        "link_bin": "https://github.com/lmbstudiocontact/mb6_6/raw/main/HalloweenGhostWitch18_M6_2_English.bin",
        "name_language": "English",
        "id_bin_language": "HalloweenGhostWitch18_M6_2_English"
      },
      {
        "author": "LMB Studio",
        "link_thumb": "https://live.staticflickr.com/65535/51676030282_62aab82790_o.gif",
        "link_bin": "https://github.com/lmbstudiocontact/mb6_6/raw/main/HalloweenGhostWitch18_M6_2_Portuguese.bin",
        "name_language": "Portuguese",
        "id_bin_language": "HalloweenGhostWitch18_M6_2_Portuguese"
      },
      {
        "author": "LMB Studio",
        "link_thumb": "https://live.staticflickr.com/65535/51677505669_f421cf6ce3_o.gif",
        "link_bin": "https://github.com/lmbstudiocontact/mb6_6/raw/main/HalloweenGhostWitch18_M6_2_Russian.bin",
        "name_language": "Russian",
        "id_bin_language": "HalloweenGhostWitch18_M6_2_Russian"
      },
      {
        "author": "LMB Studio",
        "link_thumb": "https://live.staticflickr.com/65535/51677080833_b0dfa9177a_o.gif",
        "link_bin": "https://github.com/lmbstudiocontact/mb6_6/raw/main/HalloweenGhostWitch18_M6_2_Spanish.bin",
        "name_language": "Spanish",
        "id_bin_language": "HalloweenGhostWitch18_M6_2_Spanish"
      }
    ],
    "array_tags": [],
    "list_album": [
      {
        "id_album": "-877220232",
        "link_thumb": "https://live.staticflickr.com/65535/51677079843_1303a93716_o.gif",
        "title": "Halloween Ghost Witch_M6_2"
      }
    ]
  },
  {
    "author": "Nebrit",
    "link_thumb": "https://live.staticflickr.com/65535/51668663467_9c5c7aac89_o.gif",
    "link_bin": "https://github.com/lmbstudiocontact/mb6_0/raw/main/1021.bin",
    "id_bin": "1021",
    "list_language": [],
    "array_tags": [
      "date",
      "distance",
      "heartrate",
      "english",
      "weather",
      "temperature",
      "pai",
      "calories",
      "battery",
      "steps"
    ],
    "list_album": [
      {
        "id_album": "2433880",
        "link_thumb": "https://live.staticflickr.com/65535/51668663467_9c5c7aac89_o.gif",
        "title": "None"
      }
    ]
  },
  {
    "author": "si_yuan",
    "link_thumb": "https://live.staticflickr.com/65535/51669663641_2274f6a973_o.gif",
    "link_bin": "https://github.com/lmbstudiocontact/mb6_0/raw/main/246.bin",
    "id_bin": "246",
    "list_language": [],
    "array_tags": [],
    "list_album": [
      {
        "id_album": "2211858",
        "link_thumb": "https://live.staticflickr.com/65535/51669663641_2274f6a973_o.gif",
        "title": "Game"
      }
    ]
  },
  {
    "author": "Zdan",
    "link_thumb": "https://live.staticflickr.com/65535/51670178979_09a46c43fe_o.gif",
    "link_bin": "https://github.com/lmbstudiocontact/mb6_0/raw/main/1296.bin",
    "id_bin": "1296",
    "list_language": [],
    "array_tags": [
      "date",
      "distance",
      "alarm",
      "weather",
      "weekday",
      "health",
      "calories",
      "day",
      "steps"
    ],
    "list_album": [
      {
        "id_album": "2433880",
        "link_thumb": "https://live.staticflickr.com/65535/51670178979_09a46c43fe_o.gif",
        "title": "None"
      }
    ]
  },
  {
    "author": "ZanarkTempest",
    "link_thumb": "https://live.staticflickr.com/65535/51670443820_2928e7af2a_o.gif",
    "link_bin": "https://github.com/lmbstudiocontact/mb6_1/raw/main/1814.bin",
    "id_bin": "1814",
    "list_language": [],
    "array_tags": [
      "dragonball",
      "goku",
      "anime"
    ],
    "list_album": [
      {
        "id_album": "63410260",
        "link_thumb": "https://live.staticflickr.com/65535/51670443820_2928e7af2a_o.gif",
        "title": "Anime"
      }
    ]
  },
  {
    "author": "q10243732",
    "link_thumb": "https://live.staticflickr.com/65535/51670462295_28c077e141_o.gif",
    "link_bin": "https://github.com/lmbstudiocontact/mb6_1/raw/main/1929.bin",
    "id_bin": "1929",
    "list_language": [],
    "array_tags": [
      "date",
      "weather",
      "battery",
      "steps"
    ],
    "list_album": [
      {
        "id_album": "2433880",
        "link_thumb": "https://live.staticflickr.com/65535/51670462295_28c077e141_o.gif",
        "title": "None"
      }
    ]
  },
  {
    "author": "shymik",
    "link_thumb": "https://live.staticflickr.com/65535/51670525335_ae6a374f37_o.gif",
    "link_bin": "https://github.com/lmbstudiocontact/mb6_1/raw/main/2332.bin",
    "id_bin": "2332",
    "list_language": [],
    "array_tags": [
      "digital",
      "date",
      "distance",
      "heartrate",
      "weather",
      "battery",
      "steps"
    ],
    "list_album": [
      {
        "id_album": "2433880",
        "link_thumb": "https://live.staticflickr.com/65535/51670525335_ae6a374f37_o.gif",
        "title": "None"
      }
    ]
  },
  {
    "author": "LMB Studio",
    "link_thumb": "https://live.staticflickr.com/65535/51677323815_912c5a7529_o.gif",
    "link_bin": "https://github.com/lmbstudiocontact/mb6_8/raw/main/CuteArt28_M6_2.bin",
    "id_bin": "CuteArt28_M6_2",
    "list_language": [
      {
        "author": "LMB Studio",
        "link_thumb": "https://live.staticflickr.com/65535/51676445711_66b4720fa1_o.gif",
        "link_bin": "https://github.com/lmbstudiocontact/mb6_8/raw/main/CuteArt28_M6_2_English.bin",
        "name_language": "English",
        "id_bin_language": "CuteArt28_M6_2_English"
      },
      {
        "author": "LMB Studio",
        "link_thumb": "https://live.staticflickr.com/65535/51676690383_aed8f32a37_o.gif",
        "link_bin": "https://github.com/lmbstudiocontact/mb6_8/raw/main/CuteArt28_M6_2_Portuguese.bin",
        "name_language": "Portuguese",
        "id_bin_language": "CuteArt28_M6_2_Portuguese"
      },
      {
        "author": "LMB Studio",
        "link_thumb": "https://live.staticflickr.com/65535/51677324540_9b04a2bbde_o.gif",
        "link_bin": "https://github.com/lmbstudiocontact/mb6_8/raw/main/CuteArt28_M6_2_Russian.bin",
        "name_language": "Russian",
        "id_bin_language": "CuteArt28_M6_2_Russian"
      },
      {
        "author": "LMB Studio",
        "link_thumb": "https://live.staticflickr.com/65535/51677324725_bf01a3e2a5_o.gif",
        "link_bin": "https://github.com/lmbstudiocontact/mb6_8/raw/main/CuteArt28_M6_2_Spanish.bin",
        "name_language": "Spanish",
        "id_bin_language": "CuteArt28_M6_2_Spanish"
      }
    ],
    "array_tags": [],
    "list_album": [
      {
        "id_album": "195512437",
        "link_thumb": "https://live.staticflickr.com/65535/51677323815_912c5a7529_o.gif",
        "title": "Cute Art_M6_2"
      }
    ]
  },
  {
    "author": "krewlworld",
    "link_thumb": "https://live.staticflickr.com/65535/51670021493_16651e02a0_o.gif",
    "link_bin": "https://github.com/lmbstudiocontact/mb6_0/raw/main/784.bin",
    "id_bin": "784",
    "list_language": [],
    "array_tags": [
      "digital",
      "date",
      "clear",
      "simple",
      "battery",
      "clean",
      "steps",
      "minimal",
      "bluetooth",
      "legible",
      "weather",
      "lock",
      "dnd"
    ],
    "list_album": [
      {
        "id_album": "2433880",
        "link_thumb": "https://live.staticflickr.com/65535/51670021493_16651e02a0_o.gif",
        "title": "None"
      }
    ]
  },
  {
    "author": "cyberdsign",
    "link_thumb": "https://live.staticflickr.com/65535/51668696112_2a12dee1c5_o.gif",
    "link_bin": "https://github.com/lmbstudiocontact/mb6_0/raw/main/1318.bin",
    "id_bin": "1318",
    "list_language": [],
    "array_tags": [
      "date",
      "distance",
      "heartrate",
      "battery",
      "anime"
    ],
    "list_album": [
      {
        "id_album": "63410260",
        "link_thumb": "https://live.staticflickr.com/65535/51668696112_2a12dee1c5_o.gif",
        "title": "Anime"
      }
    ]
  },
  {
    "author": "LMB Studio",
    "link_thumb": "https://live.staticflickr.com/65535/51677654429_928fb45782_o.gif",
    "link_bin": "https://github.com/lmbstudiocontact/mb6_6/raw/main/Kitty\u0026MyMelody17_M6_2.bin",
    "id_bin": "Kitty\u0026MyMelody17_M6_2",
    "list_language": [
      {
        "author": "LMB Studio",
        "link_thumb": "https://live.staticflickr.com/65535/51677864635_bc0256d218_o.gif",
        "link_bin": "https://github.com/lmbstudiocontact/mb6_6/raw/main/Kitty\u0026MyMelody17_M6_2_English.bin",
        "name_language": "English",
        "id_bin_language": "Kitty\u0026MyMelody17_M6_2_English"
      },
      {
        "author": "LMB Studio",
        "link_thumb": "https://live.staticflickr.com/65535/51676178922_bb4031126a_o.gif",
        "link_bin": "https://github.com/lmbstudiocontact/mb6_6/raw/main/Kitty\u0026MyMelody17_M6_2_Portuguese.bin",
        "name_language": "Portuguese",
        "id_bin_language": "Kitty\u0026MyMelody17_M6_2_Portuguese"
      },
      {
        "author": "LMB Studio",
        "link_thumb": "https://live.staticflickr.com/65535/51677865055_2afcdf03dd_o.gif",
        "link_bin": "https://github.com/lmbstudiocontact/mb6_6/raw/main/Kitty\u0026MyMelody17_M6_2_Russian.bin",
        "name_language": "Russian",
        "id_bin_language": "Kitty\u0026MyMelody17_M6_2_Russian"
      },
      {
        "author": "LMB Studio",
        "link_thumb": "https://live.staticflickr.com/65535/51676983271_444abd22fd_o.gif",
        "link_bin": "https://github.com/lmbstudiocontact/mb6_6/raw/main/Kitty\u0026MyMelody17_M6_2_Spanish.bin",
        "name_language": "Spanish",
        "id_bin_language": "Kitty\u0026MyMelody17_M6_2_Spanish"
      }
    ],
    "array_tags": [],
    "list_album": [
      {
        "id_album": "1352454006",
        "link_thumb": "https://live.staticflickr.com/65535/51677654429_928fb45782_o.gif",
        "title": "Kitty \u0026 My Melody_M6_2"
      }
    ]
  },
  {
    "author": "LMB Studio",
    "link_thumb": "https://live.staticflickr.com/65535/51677315651_9e728922d5_o.gif",
    "link_bin": "https://github.com/lmbstudiocontact/mb6_3/raw/main/OnePieceAnime56_M6_2.bin",
    "id_bin": "OnePieceAnime56_M6_2",
    "list_language": [
      {
        "author": "LMB Studio",
        "link_thumb": "https://live.staticflickr.com/65535/51676508677_d09589d572_o.gif",
        "link_bin": "https://github.com/lmbstudiocontact/mb6_3/raw/main/OnePieceAnime56_M6_2_English.bin",
        "name_language": "English",
        "id_bin_language": "OnePieceAnime56_M6_2_English"
      },
      {
        "author": "LMB Studio",
        "link_thumb": "https://live.staticflickr.com/65535/51676508852_93b8e73548_o.gif",
        "link_bin": "https://github.com/lmbstudiocontact/mb6_3/raw/main/OnePieceAnime56_M6_2_Portuguese.bin",
        "name_language": "Portuguese",
        "id_bin_language": "OnePieceAnime56_M6_2_Portuguese"
      },
      {
        "author": "LMB Studio",
        "link_thumb": "https://live.staticflickr.com/65535/51677988249_6dede54f3e_o.gif",
        "link_bin": "https://github.com/lmbstudiocontact/mb6_3/raw/main/OnePieceAnime56_M6_2_Russian.bin",
        "name_language": "Russian",
        "id_bin_language": "OnePieceAnime56_M6_2_Russian"
      },
      {
        "author": "LMB Studio",
        "link_thumb": "https://live.staticflickr.com/65535/51677564103_e20e9c8e46_o.gif",
        "link_bin": "https://github.com/lmbstudiocontact/mb6_3/raw/main/OnePieceAnime56_M6_2_Spanish.bin",
        "name_language": "Spanish",
        "id_bin_language": "OnePieceAnime56_M6_2_Spanish"
      }
    ],
    "array_tags": [],
    "list_album": [
      {
        "id_album": "1669710643",
        "link_thumb": "https://live.staticflickr.com/65535/51677315651_9e728922d5_o.gif",
        "title": "One Piece Anime_M6_2"
      }
    ]
  },
  {
    "author": "kvdkvd",
    "link_thumb": "https://live.staticflickr.com/65535/51670672285_20b9ac5e16_o.gif",
    "link_bin": "https://github.com/lmbstudiocontact/mb6_0/raw/main/852.bin",
    "id_bin": "852",
    "list_language": [],
    "array_tags": [
      "digital",
      "date",
      "distance",
      "heartrate",
      "weather",
      "calories",
      "battery",
      "steps"
    ],
    "list_album": [
      {
        "id_album": "2433880",
        "link_thumb": "https://live.staticflickr.com/65535/51670672285_20b9ac5e16_o.gif",
        "title": "None"
      }
    ]
  },
  {
    "author": "LMB Studio",
    "link_thumb": "https://live.staticflickr.com/65535/51676838912_6c7c99e745_o.gif",
    "link_bin": "https://github.com/lmbstudiocontact/mb6_4/raw/main/Shiv22_M6_2.bin",
    "id_bin": "Shiv22_M6_2",
    "list_language": [
      {
        "author": "LMB Studio",
        "link_thumb": "https://live.staticflickr.com/65535/51678318144_d95a931c76_o.gif",
        "link_bin": "https://github.com/lmbstudiocontact/mb6_4/raw/main/Shiv22_M6_2_English.bin",
        "name_language": "English",
        "id_bin_language": "Shiv22_M6_2_English"
      },
      {
        "author": "LMB Studio",
        "link_thumb": "https://live.staticflickr.com/65535/51676839192_d3c9141796_o.gif",
        "link_bin": "https://github.com/lmbstudiocontact/mb6_4/raw/main/Shiv22_M6_2_Portuguese.bin",
        "name_language": "Portuguese",
        "id_bin_language": "Shiv22_M6_2_Portuguese"
      },
      {
        "author": "LMB Studio",
        "link_thumb": "https://live.staticflickr.com/65535/51678526040_e77b12746a_o.gif",
        "link_bin": "https://github.com/lmbstudiocontact/mb6_4/raw/main/Shiv22_M6_2_Russian.bin",
        "name_language": "Russian",
        "id_bin_language": "Shiv22_M6_2_Russian"
      },
      {
        "author": "LMB Studio",
        "link_thumb": "https://live.staticflickr.com/65535/51678526215_cee7df5305_o.gif",
        "link_bin": "https://github.com/lmbstudiocontact/mb6_4/raw/main/Shiv22_M6_2_Spanish.bin",
        "name_language": "Spanish",
        "id_bin_language": "Shiv22_M6_2_Spanish"
      }
    ],
    "array_tags": [],
    "list_album": [
      {
        "id_album": "-959254855",
        "link_thumb": "https://live.staticflickr.com/65535/51676838912_6c7c99e745_o.gif",
        "title": "Shiv_M6_2"
      }
    ]
  },
  {
    "author": "None",
    "link_thumb": "https://live.staticflickr.com/65535/51669520381_25500dc344_o.gif",
    "link_bin": "https://github.com/lmbstudiocontact/mb6_0/raw/main/1519.bin",
    "id_bin": "1519",
    "list_language": [],
    "array_tags": [
      "digital",
      "date",
      "analog",
      "heartrate",
      "alarm",
      "battery",
      "steps",
      "status"
    ],
    "list_album": [
      {
        "id_album": "2433880",
        "link_thumb": "https://live.staticflickr.com/65535/51669520381_25500dc344_o.gif",
        "title": "None"
      }
    ]
  },
  {
    "author": "LMB Studio",
    "link_thumb": "https://live.staticflickr.com/65535/51677382223_275ddf937b_o.gif",
    "link_bin": "https://github.com/lmbstudiocontact/mb6_7/raw/main/MoanaCartoon1_M6_2.bin",
    "id_bin": "MoanaCartoon1_M6_2",
    "list_language": [
      {
        "author": "LMB Studio",
        "link_thumb": "https://live.staticflickr.com/65535/51677134736_de5c386fdf_o.gif",
        "link_bin": "https://github.com/lmbstudiocontact/mb6_7/raw/main/MoanaCartoon1_M6_2_English.bin",
        "name_language": "English",
        "id_bin_language": "MoanaCartoon1_M6_2_English"
      },
      {
        "author": "LMB Studio",
        "link_thumb": "https://live.staticflickr.com/65535/51676329952_731f377f2f_o.gif",
        "link_bin": "https://github.com/lmbstudiocontact/mb6_7/raw/main/MoanaCartoon1_M6_2_Portuguese.bin",
        "name_language": "Portuguese",
        "id_bin_language": "MoanaCartoon1_M6_2_Portuguese"
      },
      {
        "author": "LMB Studio",
        "link_thumb": "https://live.staticflickr.com/65535/51676330297_26b5d174aa_o.gif",
        "link_bin": "https://github.com/lmbstudiocontact/mb6_7/raw/main/MoanaCartoon1_M6_2_Russian.bin",
        "name_language": "Russian",
        "id_bin_language": "MoanaCartoon1_M6_2_Russian"
      },
      {
        "author": "LMB Studio",
        "link_thumb": "https://live.staticflickr.com/65535/51677383228_3dfd4b48a3_o.gif",
        "link_bin": "https://github.com/lmbstudiocontact/mb6_7/raw/main/MoanaCartoon1_M6_2_Spanish.bin",
        "name_language": "Spanish",
        "id_bin_language": "MoanaCartoon1_M6_2_Spanish"
      }
    ],
    "array_tags": [],
    "list_album": [
      {
        "id_album": "-1260016165",
        "link_thumb": "https://live.staticflickr.com/65535/51677382223_275ddf937b_o.gif",
        "title": "Moana Cartoon_M6_2"
      }
    ]
  },
  {
    "author": "aquaporcy",
    "link_thumb": "https://live.staticflickr.com/65535/51668801107_f500765b95_o.gif",
    "link_bin": "https://github.com/lmbstudiocontact/mb6_1/raw/main/2040.bin",
    "id_bin": "2040",
    "list_language": [],
    "array_tags": [],
    "list_album": [
      {
        "id_album": "63410260",
        "link_thumb": "https://live.staticflickr.com/65535/51668801107_f500765b95_o.gif",
        "title": "Anime"
      }
    ]
  },
  {
    "author": "neux",
    "link_thumb": "https://live.staticflickr.com/65535/51669529466_e7772a8e1b_o.gif",
    "link_bin": "https://github.com/lmbstudiocontact/mb6_0/raw/main/1605.bin",
    "id_bin": "1605",
    "list_language": [],
    "array_tags": [
      "date",
      "black",
      "weather",
      "battery",
      "sport",
      "steps"
    ],
    "list_album": [
      {
        "id_album": "2433880",
        "link_thumb": "https://live.staticflickr.com/65535/51669529466_e7772a8e1b_o.gif",
        "title": "None"
      }
    ]
  },
  {
    "author": "Nebrit",
    "link_thumb": "https://live.staticflickr.com/65535/51669714208_9df24890f4_o.gif",
    "link_bin": "https://github.com/lmbstudiocontact/mb6_0/raw/main/1113.bin",
    "id_bin": "1113",
    "list_language": [],
    "array_tags": [
      "date",
      "digital",
      "distance",
      "heartrate",
      "weather",
      "temperature",
      "pai",
      "calories",
      "battery",
      "steps"
    ],
    "list_album": [
      {
        "id_album": "2433880",
        "link_thumb": "https://live.staticflickr.com/65535/51669714208_9df24890f4_o.gif",
        "title": "None"
      }
    ]
  },
  {
    "author": "LMB Studio",
    "link_thumb": "https://live.staticflickr.com/65535/51676777801_413e189676_o.gif",
    "link_bin": "https://github.com/lmbstudiocontact/mb6_2/raw/main/Football8_M6_2.bin",
    "id_bin": "Football8_M6_2",
    "list_language": [
      {
        "author": "LMB Studio",
        "link_thumb": "https://live.staticflickr.com/65535/51677024593_f587d6fd93_o.gif",
        "link_bin": "https://github.com/lmbstudiocontact/mb6_2/raw/main/Football8_M6_2_English.bin",
        "name_language": "English",
        "id_bin_language": "Football8_M6_2_English"
      },
      {
        "author": "LMB Studio",
        "link_thumb": "https://live.staticflickr.com/65535/51677024813_26587e2aab_o.gif",
        "link_bin": "https://github.com/lmbstudiocontact/mb6_2/raw/main/Football8_M6_2_Portuguese.bin",
        "name_language": "Portuguese",
        "id_bin_language": "Football8_M6_2_Portuguese"
      },
      {
        "author": "LMB Studio",
        "link_thumb": "https://live.staticflickr.com/65535/51677449959_4d28b33641_o.gif",
        "link_bin": "https://github.com/lmbstudiocontact/mb6_2/raw/main/Football8_M6_2_Russian.bin",
        "name_language": "Russian",
        "id_bin_language": "Football8_M6_2_Russian"
      },
      {
        "author": "LMB Studio",
        "link_thumb": "https://live.staticflickr.com/65535/51677025443_042f7cb622_o.gif",
        "link_bin": "https://github.com/lmbstudiocontact/mb6_2/raw/main/Football8_M6_2_Spanish.bin",
        "name_language": "Spanish",
        "id_bin_language": "Football8_M6_2_Spanish"
      }
    ],
    "array_tags": [],
    "list_album": [
      {
        "id_album": "-73748370",
        "link_thumb": "https://live.staticflickr.com/65535/51676777801_413e189676_o.gif",
        "title": "Football_M6_2"
      }
    ]
  },
  {
    "author": "DaddyPWNZ",
    "link_thumb": "https://live.staticflickr.com/65535/51668849952_9b496617ce_o.gif",
    "link_bin": "https://github.com/lmbstudiocontact/mb6_0/raw/main/234.bin",
    "id_bin": "234",
    "list_language": [],
    "array_tags": [
      "digital",
      "date",
      "heartrate",
      "battery",
      "steps"
    ],
    "list_album": [
      {
        "id_album": "-2075887794",
        "link_thumb": "https://live.staticflickr.com/65535/51668849952_9b496617ce_o.gif",
        "title": "Cartoon"
      }
    ]
  },
  {
    "author": "LMB Studio",
    "link_thumb": "https://live.staticflickr.com/65535/51677776428_0933038e80_o.gif",
    "link_bin": "https://github.com/lmbstudiocontact/mb6_9/raw/main/PokmonAnime88_M6_2.bin",
    "id_bin": "PokmonAnime88_M6_2",
    "list_language": [
      {
        "author": "LMB Studio",
        "link_thumb": "https://live.staticflickr.com/65535/51677528871_d16c6a42ab_o.gif",
        "link_bin": "https://github.com/lmbstudiocontact/mb6_9/raw/main/PokmonAnime88_M6_2_English.bin",
        "name_language": "English",
        "id_bin_language": "PokmonAnime88_M6_2_English"
      },
      {
        "author": "LMB Studio",
        "link_thumb": "https://live.staticflickr.com/65535/51678408545_d327aed72a_o.gif",
        "link_bin": "https://github.com/lmbstudiocontact/mb6_9/raw/main/PokmonAnime88_M6_2_Portuguese.bin",
        "name_language": "Portuguese",
        "id_bin_language": "PokmonAnime88_M6_2_Portuguese"
      },
      {
        "author": "LMB Studio",
        "link_thumb": "https://live.staticflickr.com/65535/51678408735_8527802b0c_o.gif",
        "link_bin": "https://github.com/lmbstudiocontact/mb6_9/raw/main/PokmonAnime88_M6_2_Russian.bin",
        "name_language": "Russian",
        "id_bin_language": "PokmonAnime88_M6_2_Russian"
      },
      {
        "author": "LMB Studio",
        "link_thumb": "https://live.staticflickr.com/65535/51678408945_ef05857911_o.gif",
        "link_bin": "https://github.com/lmbstudiocontact/mb6_9/raw/main/PokmonAnime88_M6_2_Spanish.bin",
        "name_language": "Spanish",
        "id_bin_language": "PokmonAnime88_M6_2_Spanish"
      }
    ],
    "array_tags": [],
    "list_album": [
      {
        "id_album": "-1571020089",
        "link_thumb": "https://live.staticflickr.com/65535/51677776428_0933038e80_o.gif",
        "title": "Pokmon Anime_M6_2"
      }
    ]
  },
  {
    "author": "KrakeCZ",
    "link_thumb": "https://live.staticflickr.com/65535/51670151804_91d31e90db_o.gif",
    "link_bin": "https://github.com/lmbstudiocontact/mb6_0/raw/main/1041.bin",
    "id_bin": "1041",
    "list_language": [],
    "array_tags": [
      "digital",
      "date",
      "distance",
      "heartrate",
      "weather",
      "calories",
      "battery",
      "steps"
    ],
    "list_album": [
      {
        "id_album": "2433880",
        "link_thumb": "https://live.staticflickr.com/65535/51670151804_91d31e90db_o.gif",
        "title": "None"
      }
    ]
  },
  {
    "author": "LMB Studio",
    "link_thumb": "https://live.staticflickr.com/65535/51676876341_524804e42e_o.gif",
    "link_bin": "https://github.com/lmbstudiocontact/mb6_6/raw/main/HalloweenGhostWitch47_M6_2.bin",
    "id_bin": "HalloweenGhostWitch47_M6_2",
    "list_language": [
      {
        "author": "LMB Studio",
        "link_thumb": "https://live.staticflickr.com/65535/51677758380_c4658084e1_o.gif",
        "link_bin": "https://github.com/lmbstudiocontact/mb6_6/raw/main/HalloweenGhostWitch47_M6_2_English.bin",
        "name_language": "English",
        "id_bin_language": "HalloweenGhostWitch47_M6_2_English"
      },
      {
        "author": "LMB Studio",
        "link_thumb": "https://live.staticflickr.com/65535/51676876886_3d6e227968_o.gif",
        "link_bin": "https://github.com/lmbstudiocontact/mb6_6/raw/main/HalloweenGhostWitch47_M6_2_Portuguese.bin",
        "name_language": "Portuguese",
        "id_bin_language": "HalloweenGhostWitch47_M6_2_Portuguese"
      },
      {
        "author": "LMB Studio",
        "link_thumb": "https://live.staticflickr.com/65535/51677758885_b0c9bab5c8_o.gif",
        "link_bin": "https://github.com/lmbstudiocontact/mb6_6/raw/main/HalloweenGhostWitch47_M6_2_Russian.bin",
        "name_language": "Russian",
        "id_bin_language": "HalloweenGhostWitch47_M6_2_Russian"
      },
      {
        "author": "LMB Studio",
        "link_thumb": "https://live.staticflickr.com/65535/51676074252_3cf07c7b7b_o.gif",
        "link_bin": "https://github.com/lmbstudiocontact/mb6_6/raw/main/HalloweenGhostWitch47_M6_2_Spanish.bin",
        "name_language": "Spanish",
        "id_bin_language": "HalloweenGhostWitch47_M6_2_Spanish"
      }
    ],
    "array_tags": [],
    "list_album": [
      {
        "id_album": "-877220232",
        "link_thumb": "https://live.staticflickr.com/65535/51676876341_524804e42e_o.gif",
        "title": "Halloween Ghost Witch_M6_2"
      }
    ]
  }
]